parametric_umap/__init__.py
parametric_umap/core.py
parametric_umap/datasets/__init__.py
parametric_umap/datasets/covariates_datasets.py
parametric_umap/datasets/edge_dataset.py
parametric_umap/models/__init__.py
parametric_umap/models/mlp.py
parametric_umap/utils/__init__.py
parametric_umap/utils/graph.py
parametric_umap/utils/losses.py
parametric_umap-0.1.2.dist-info/LICENSE
parametric_umap-0.1.2.dist-info/METADATA
parametric_umap-0.1.2.dist-info/WHEEL
parametric_umap-0.1.2.dist-info/RECORD
