Metadata-Version: 2.3
Name: parametric-umap
Version: 0.1.2
Summary: A streamlined and fast implementation of parametric UMAP using PyTorch and FAISS
License: BSD License
Author: Francesco Carli
Author-email: francesco.carli94@gmail.com
Requires-Python: >=3.10
Classifier: License :: Other/Proprietary License
Classifier: Programming Language :: Python :: 3
Classifier: Programming Language :: Python :: 3.10
Classifier: Programming Language :: Python :: 3.11
Classifier: Programming Language :: Python :: 3.12
Classifier: Programming Language :: Python :: 3.13
Requires-Dist: faiss-cpu (>=1.10.0,<2.0.0)
Requires-Dist: numpy (>=2.2.3,<3.0.0)
Requires-Dist: scipy (>=1.15.2,<2.0.0)
Requires-Dist: torch (>=2.1.0,<3.0.0)
Requires-Dist: tqdm (>=4.67.1,<5.0.0)
